samples/__init__.py
samples/ping_test.py
samples/send_message.py
telegrapi/__init__.py
telegrapi/api.py
telegrapi/method.py
telegrapi-1.0.0.dist-info/LICENSE
telegrapi-1.0.0.dist-info/METADATA
telegrapi-1.0.0.dist-info/WHEEL
telegrapi-1.0.0.dist-info/top_level.txt
telegrapi-1.0.0.dist-info/RECORD
